wally_dev/__init__.py
wally_dev/__main__.py
wally_dev/api_client.py
wally_dev/cli.py
wally_dev/config.py
wally_dev/constants.py
wally_dev/exceptions.py
wally_dev/generator.py
wally_dev/models.py
wally_dev/py.typed
wally_dev/runner.py
wally_dev/workspace.py
wally_dev/commands/__init__.py
wally_dev/commands/checkout.py
wally_dev/commands/login.py
wally_dev/commands/logout.py
wally_dev/commands/norms.py
wally_dev/commands/organizations.py
wally_dev/commands/push.py
wally_dev/commands/rules.py
wally_dev/commands/run.py
wally_dev/commands/status.py
wally_dev/commands/testcases.py
wally_dev-0.0.1.dist-info/licenses/LICENSE
wally_dev-0.0.1.dist-info/METADATA
wally_dev-0.0.1.dist-info/WHEEL
wally_dev-0.0.1.dist-info/entry_points.txt
wally_dev-0.0.1.dist-info/top_level.txt
wally_dev-0.0.1.dist-info/RECORD
