Metadata-Version: 2.4
Name: wally-dev
Version: 0.0.1
Summary: CLI para desenvolvimento local de casos de teste de acessibilidade da plataforma Wally
Author-email: Equallyze <contato@equallyze.com>
Maintainer-email: Equallyze <contato@equallyze.com>
License-Expression: LicenseRef-Proprietary
Project-URL: Homepage, https://acessibilidade.global
Project-URL: Documentation, https://docs.acessibilidade.global
Project-URL: Repository, https://gitlab.com/AcessibilidadeParaTodos/wally/wally-dev
Project-URL: Issues, https://gitlab.com/AcessibilidadeParaTodos/wally/wally-dev/-/issues
Project-URL: Changelog, https://gitlab.com/AcessibilidadeParaTodos/wally/wally-dev/-/blob/main/CHANGELOG.md
Keywords: accessibility,a11y,testing,cli,wally,equallyze,acessibilidade,nbr17225
Classifier: Development Status :: 4 - Beta
Classifier: Environment :: Console
Classifier: Intended Audience :: Developers
Classifier: Operating System :: OS Independent
Classifier: Programming Language :: Python :: 3
Classifier: Programming Language :: Python :: 3.9
Classifier: Programming Language :: Python :: 3.10
Classifier: Programming Language :: Python :: 3.11
Classifier: Programming Language :: Python :: 3.12
Classifier: Programming Language :: Python :: 3.13
Classifier: Topic :: Software Development :: Testing
Classifier: Topic :: Software Development :: Quality Assurance
Classifier: Topic :: Internet :: WWW/HTTP :: Site Management
Classifier: Typing :: Typed
Requires-Python: >=3.9
License-File: LICENSE
Requires-Dist: requests<3.0.0,>=2.31.0
Requires-Dist: pydantic<3.0.0,>=2.5.0
Requires-Dist: pydantic-settings<3.0.0,>=2.1.0
Requires-Dist: python-dotenv<2.0.0,>=1.0.0
Requires-Dist: click<9.0.0,>=8.1.0
Requires-Dist: rich<14.0.0,>=13.0.0
Requires-Dist: beautifulsoup4<5.0.0,>=4.12.0
Provides-Extra: ai
Requires-Dist: openai<2.0.0,>=1.0.0; extra == "ai"
Provides-Extra: dev
Requires-Dist: pytest>=7.4.0; extra == "dev"
Requires-Dist: pytest-cov>=4.1.0; extra == "dev"
Requires-Dist: pytest-mock>=3.12.0; extra == "dev"
Requires-Dist: responses>=0.24.0; extra == "dev"
Requires-Dist: black>=23.0.0; extra == "dev"
Requires-Dist: isort>=5.12.0; extra == "dev"
Requires-Dist: mypy>=1.7.0; extra == "dev"
Requires-Dist: ruff>=0.1.0; extra == "dev"
Requires-Dist: types-requests>=2.31.0; extra == "dev"
Requires-Dist: types-beautifulsoup4>=4.12.0; extra == "dev"
Requires-Dist: pre-commit>=3.5.0; extra == "dev"
Requires-Dist: openai<2.0.0,>=1.0.0; extra == "dev"
Dynamic: license-file
